jupiterhelper/__init__.py
jupiterhelper/helper.py
jupiterhelper-0.1.6.dist-info/METADATA
jupiterhelper-0.1.6.dist-info/WHEEL
jupiterhelper-0.1.6.dist-info/entry_points.txt
jupiterhelper-0.1.6.dist-info/top_level.txt
jupiterhelper-0.1.6.dist-info/RECORD
