Metadata-Version: 2.1
Name: jupiterhelper
Version: 0.1.6
Requires-Dist: requests
